mio_package/__init__.py
mio_package/core.py
mio_package-0.1.1.dist-info/METADATA
mio_package-0.1.1.dist-info/WHEEL
mio_package-0.1.1.dist-info/licenses/LICENSE
mio_package-0.1.1.dist-info/RECORD
