Metadata-Version: 2.4
Name: mio-package
Version: 0.1.1
Summary: Un semplice package di esempio
Project-URL: Homepage, https://github.com/antonellomangone/mio-package
Project-URL: Bug Tracker, https://github.com/antonellomangone/mio-package/issues
Author-email: theant72 <antonello.mangone@gmail.com>
License-File: LICENSE
Requires-Python: >=3.12
